MANIFEST.in
README.txt
setup.cfg
setup.py
docs/HISTORY.txt
docs/INSTALL.txt
docs/LICENSE.GPL
docs/LICENSE.txt
jalon/__init__.py
jalon.edit.egg-info/PKG-INFO
jalon.edit.egg-info/SOURCES.txt
jalon.edit.egg-info/dependency_links.txt
jalon.edit.egg-info/entry_points.txt
jalon.edit.egg-info/namespace_packages.txt
jalon.edit.egg-info/not-zip-safe
jalon.edit.egg-info/paster_plugins.txt
jalon.edit.egg-info/requires.txt
jalon.edit.egg-info/top_level.txt
jalon/edit/__init__.py
jalon/edit/configure.zcml
jalon/edit/setuphandlers.py
jalon/edit/tests.py
jalon/edit/portlets/__init__.py
jalon/edit/portlets/configure.zcml
jalon/edit/portlets/interfaces.py
jalon/edit/portlets/presentation.py
jalon/edit/portlets/ressource.py
jalon/edit/portlets/templates/ressource.pt
jalon/edit/profiles/default/jalon.edit-install.txt
jalon/edit/profiles/default/jalon.edit-various-.txt
jalon/edit/profiles/default/metadata.xml
jalon/edit/profiles/default/portlets.xml
jalon/edit/profiles/default/properties.xml
jalon/edit/profiles/default/rolemap.xml
jalon/edit/profiles/default/types.xml
jalon/edit/profiles/default/workflows.xml
jalon/edit/profiles/default/structure/.objects
jalon/edit/profiles/default/structure/.properties
jalon/edit/profiles/default/structure/front-page
jalon/edit/profiles/default/structure/Members/.objects
jalon/edit/profiles/default/structure/Members/.properties
jalon/edit/profiles/default/structure/cours/.objects
jalon/edit/profiles/default/structure/cours/.properties
jalon/edit/profiles/default/structure/cours/aide
jalon/edit/profiles/default/structure/cours/credits
jalon/edit/profiles/default/structure/cours/mentions
jalon/edit/profiles/default/structure/cours/bibliographie/.objects
jalon/edit/profiles/default/structure/cours/bibliographie/.properties
jalon/edit/profiles/default/structure/cours/fichiers/.objects
jalon/edit/profiles/default/structure/cours/fichiers/.properties
jalon/edit/profiles/default/structure/cours/glossaire/.objects
jalon/edit/profiles/default/structure/cours/glossaire/.properties
jalon/edit/profiles/default/structure/cours/presentation/.objects
jalon/edit/profiles/default/structure/cours/presentation/.properties
jalon/edit/profiles/default/structure/cours/webographie/.objects
jalon/edit/profiles/default/structure/cours/webographie/.properties
